cpelib/__init__.py
cpelib/core/__init__.py
cpelib/core/loaders/__init__.py
cpelib/core/loaders/base.py
cpelib/core/loaders/json.py
cpelib/core/loaders/xml.py
cpelib/types/__init__.py
cpelib/types/cpe.py
cpelib/types/definitions.py
cpelib/types/dictionary.py
cpelib/types/generator.py
cpelib/types/item.py
cpelib/types/product.py
cpelib/types/reference.py
cpelib/types/vendor.py
cpelib/utils/__init__.py
cpelib/utils/common.py
examples/count_deprecated_items.py
examples/count_vendors_products.py
examples/cpe_dict_to_json.py
examples/load_from_json.py
examples/load_references_for_product.py
cpelib-0.2.0.dist-info/LICENSE
cpelib-0.2.0.dist-info/METADATA
cpelib-0.2.0.dist-info/WHEEL
cpelib-0.2.0.dist-info/top_level.txt
cpelib-0.2.0.dist-info/RECORD
