Metadata-Version: 2.2
Name: cpelib
Version: 0.2.0
Summary: A Python package for parsing, representing, and filtering the NVD CPE Dictionary.
Author-email: Eduard Pinconschi <eduard.pinconschi@tecnico.ulisboa.pt>
Project-URL: repository, https://github.com/epicosy/cpelib
Project-URL: homepage, https://github.com/epicosy/cpelib
Keywords: package,nvd,cpe
Classifier: Topic :: Software Development
Classifier: Programming Language :: Python
Classifier: Environment :: Console
Classifier: Intended Audience :: Developers
Requires-Python: >=3.9
License-File: LICENSE
Requires-Dist: lxml>=5.3.0
Requires-Dist: pydantic>=2.10.3
Requires-Dist: tqdm>=4.67.1
Requires-Dist: cpeparser>=0.0.2
Provides-Extra: test
Requires-Dist: pytest; extra == "test"
Requires-Dist: pytest-cov; extra == "test"
Requires-Dist: coverage; extra == "test"
Requires-Dist: twine>=1.11.0; extra == "test"
Requires-Dist: setuptools>=38.6.0; extra == "test"
Requires-Dist: wheel>=0.31.0; extra == "test"
